MANIFEST.in
setup.py
farbox_bucket/LICENSE.py
farbox_bucket/__init__.py
farbox_bucket/console.py
farbox_bucket/settings.py
farbox_bucket/test_sync.py
farbox_bucket.egg-info/PKG-INFO
farbox_bucket.egg-info/SOURCES.txt
farbox_bucket.egg-info/dependency_links.txt
farbox_bucket.egg-info/entry_points.txt
farbox_bucket.egg-info/requires.txt
farbox_bucket.egg-info/top_level.txt
farbox_bucket/bitcron/__init__.py
farbox_bucket/bitcron/bitcron_meta.py
farbox_bucket/bitcron/bitcron_meta_handler.py
farbox_bucket/bitcron/bitcron_sync_from.py
farbox_bucket/bitcron/bitcron_utils.py
farbox_bucket/bucket/__init__.py
farbox_bucket/bucket/create.py
farbox_bucket/bucket/defaults.py
farbox_bucket/bucket/delete.py
farbox_bucket/bucket/invite.py
farbox_bucket/bucket/node.py
farbox_bucket/bucket/private_configs.py
farbox_bucket/bucket/status.py
farbox_bucket/bucket/utils.py
farbox_bucket/bucket/clouds/__init__.py
farbox_bucket/bucket/clouds/storage/__init__.py
farbox_bucket/bucket/clouds/storage/qcloud.py
farbox_bucket/bucket/domain/__init__.py
farbox_bucket/bucket/domain/info.py
farbox_bucket/bucket/domain/register.py
farbox_bucket/bucket/domain/ssl_utils.py
farbox_bucket/bucket/domain/utils.py
farbox_bucket/bucket/domain/web_utils.py
farbox_bucket/bucket/helper/__init__.py
farbox_bucket/bucket/helper/files_related.py
farbox_bucket/bucket/helper/loop_buckets.py
farbox_bucket/bucket/helper/repair.py
farbox_bucket/bucket/record/__init__.py
farbox_bucket/bucket/record/create.py
farbox_bucket/bucket/record/reset.py
farbox_bucket/bucket/record/update.py
farbox_bucket/bucket/record/utils.py
farbox_bucket/bucket/record/get/__init__.py
farbox_bucket/bucket/record/get/folder.py
farbox_bucket/bucket/record/get/get.py
farbox_bucket/bucket/record/get/helper.py
farbox_bucket/bucket/record/get/mix.py
farbox_bucket/bucket/record/get/path_related.py
farbox_bucket/bucket/record/get/refer_doc_related.py
farbox_bucket/bucket/record/get/slash_related.py
farbox_bucket/bucket/record/get/tag_related.py
farbox_bucket/bucket/record/get/utils.py
farbox_bucket/bucket/record/helper/__init__.py
farbox_bucket/bucket/record/helper/update_record.py
farbox_bucket/bucket/record/related/__init__.py
