Metadata-Version: 1.0
Name: farbox-bucket
Version: 0.2060
Summary: FarBox Bucket
Home-page: UNKNOWN
Author: Hepochen
Author-email: hepochen@gmail.com
License: UNKNOWN
Platform: linux
